rapida/__init__.py
rapida/version.py
rapida/agentkit/__init__.py
rapida/clients/__init__.py
rapida/clients/assistant.py
rapida/clients/call.py
rapida/clients/endpoint.py
rapida/clients/invoke.py
rapida/clients/protos/__init__.py
rapida/clients/protos/assistant_analysis_pb2.py
rapida/clients/protos/assistant_analysis_pb2.pyi
rapida/clients/protos/assistant_analysis_pb2_grpc.py
rapida/clients/protos/assistant_api_pb2.py
rapida/clients/protos/assistant_api_pb2.pyi
rapida/clients/protos/assistant_api_pb2_grpc.py
rapida/clients/protos/assistant_deployment_pb2.py
rapida/clients/protos/assistant_deployment_pb2.pyi
rapida/clients/protos/assistant_deployment_pb2_grpc.py
rapida/clients/protos/assistant_knowledge_pb2.py
rapida/clients/protos/assistant_knowledge_pb2.pyi
rapida/clients/protos/assistant_knowledge_pb2_grpc.py
rapida/clients/protos/assistant_provider_pb2.py
rapida/clients/protos/assistant_provider_pb2.pyi
rapida/clients/protos/assistant_provider_pb2_grpc.py
rapida/clients/protos/assistant_tool_pb2.py
rapida/clients/protos/assistant_tool_pb2.pyi
rapida/clients/protos/assistant_tool_pb2_grpc.py
rapida/clients/protos/assistant_webhook_pb2.py
rapida/clients/protos/assistant_webhook_pb2.pyi
rapida/clients/protos/assistant_webhook_pb2_grpc.py
rapida/clients/protos/audit_logging_api_pb2.py
rapida/clients/protos/audit_logging_api_pb2.pyi
rapida/clients/protos/audit_logging_api_pb2_grpc.py
rapida/clients/protos/common_pb2.py
rapida/clients/protos/common_pb2.pyi
rapida/clients/protos/common_pb2_grpc.py
rapida/clients/protos/connect_api_pb2.py
rapida/clients/protos/connect_api_pb2.pyi
rapida/clients/protos/connect_api_pb2_grpc.py
rapida/clients/protos/document_api_pb2.py
rapida/clients/protos/document_api_pb2.pyi
rapida/clients/protos/document_api_pb2_grpc.py
rapida/clients/protos/endpoint_api_pb2.py
rapida/clients/protos/endpoint_api_pb2.pyi
rapida/clients/protos/endpoint_api_pb2_grpc.py
rapida/clients/protos/integration_api_pb2.py
rapida_python-0.1.25.dist-info/METADATA
rapida_python-0.1.25.dist-info/WHEEL
rapida_python-0.1.25.dist-info/top_level.txt
rapida_python-0.1.25.dist-info/RECORD
