Metadata-Version: 2.4
Name: rapida-python
Version: 0.1.25
Summary: RapidaAI SDK to integrate rapida.ai APIs
Author-email: RapidaAI <code@rapida.ai>
License-Expression: MIT
Project-URL: Homepage, https://github.com/rapidaai/rapida-python
Project-URL: Bug Reports, https://github.com/rapidaai/rapida-python/issues
Project-URL: Documentation, https://rapida.ai/docs
Project-URL: Source, https://github.com/rapidaai/rapida-python
Classifier: Development Status :: 5 - Production/Stable
Classifier: Intended Audience :: Developers
Classifier: Operating System :: OS Independent
Classifier: Programming Language :: Python
Classifier: Programming Language :: Python :: 3
Classifier: Programming Language :: Python :: 3.9
Classifier: Programming Language :: Python :: 3.10
Classifier: Programming Language :: Python :: 3.11
Classifier: Topic :: Software Development :: Libraries :: Python Modules
Requires-Python: >=3.9
Requires-Dist: protobuf
Requires-Dist: grpcio
Requires-Dist: grpcio-tools
Provides-Extra: dev
Requires-Dist: pytest; extra == "dev"
Requires-Dist: pytest-cov; extra == "dev"
Requires-Dist: flake8; extra == "dev"
Requires-Dist: black; extra == "dev"
Requires-Dist: mypy; extra == "dev"
